swedishelf/__init__.py
swedishelf/fileop.py
swedishelf/main.py
swedishelf/sven.py
swedishelf-0.1.1.dist-info/licenses/LICENSE
swedishelf-0.1.1.dist-info/METADATA
swedishelf-0.1.1.dist-info/WHEEL
swedishelf-0.1.1.dist-info/entry_points.txt
swedishelf-0.1.1.dist-info/top_level.txt
swedishelf-0.1.1.dist-info/RECORD
