Metadata-Version: 2.4
Name: swedishelf
Version: 0.1.1
Summary: An interactive command-line tool for learning Swedish through quizzes and exercises. Features vocabulary practice and grammar drills to help English speakers master Swedish efficiently.
Author-email: "Anton(Shuqiao) Li" <real.celestialli@gmail.com>
License: MIT
Keywords: swedish,english,swedish-learning,language-learning,cli-tool,vocabulary-quiz,grammar-practice,interactive-learning,education,linguistics,scandinavian-languages,language,learn,quiz,exam
Classifier: Development Status :: 5 - Production/Stable
Classifier: Environment :: Console
Classifier: Intended Audience :: Education
Classifier: Intended Audience :: Science/Research
Classifier: Natural Language :: English
Classifier: Natural Language :: Swedish
Classifier: Topic :: Text Processing
Classifier: Topic :: Text Processing :: General
Classifier: Topic :: Text Processing :: Linguistic
Classifier: Operating System :: OS Independent
Classifier: Programming Language :: Python :: 3.7
Classifier: Programming Language :: Python :: 3.8
Classifier: Programming Language :: Python :: 3.9
Classifier: Programming Language :: Python :: 3.10
Classifier: Programming Language :: Python :: 3.11
Classifier: Programming Language :: Python :: 3.12
Classifier: Programming Language :: Python :: 3.13
Requires-Python: <3.14,>=3.7
License-File: LICENSE
Requires-Dist: requests
Requires-Dist: playsound3==3.2.4
Requires-Dist: click>=8.1.8
Dynamic: license-file
